bigO/BigO.py
bigO/__init__.py
bigO/algorithm.py
bigO/utils.py
bigO/version.py
src/__init__.py
src/bigO.py
big_O_calculator-0.0.9.8.4.dist-info/LICENSE
big_O_calculator-0.0.9.8.4.dist-info/METADATA
big_O_calculator-0.0.9.8.4.dist-info/WHEEL
big_O_calculator-0.0.9.8.4.dist-info/top_level.txt
big_O_calculator-0.0.9.8.4.dist-info/RECORD
