Metadata-Version: 2.1
Name: big-O-calculator
Version: 0.0.9.8.4
Summary: A calculator to predict big-O of sorting functions
Home-page: https://github.com/Alfex4936
Author: Seok Won
Author-email: ikr@kakao.com
License: MIT
Platform: UNKNOWN
Classifier: Programming Language :: Python :: 3
Classifier: License :: OSI Approved :: MIT License
Classifier: Operating System :: OS Independent
Requires-Python: >=3.6
